result_companion/__init__.py
result_companion/core/analizers/__init__.py
result_companion/core/analizers/common.py
result_companion/core/analizers/factory_common.py
result_companion/core/analizers/local/__init__.py
result_companion/core/analizers/local/ollama_exceptions.py
result_companion/core/analizers/local/ollama_install.py
result_companion/core/analizers/local/ollama_runner.py
result_companion/core/analizers/local/ollama_server_manager.py
result_companion/core/analizers/models.py
result_companion/core/analizers/remote/__init__.py
result_companion/core/analizers/remote/custom_endpoint.py
result_companion/core/analizers/remote/openai.py
result_companion/core/chunking/chunking.py
result_companion/core/chunking/utils.py
result_companion/core/configs/default_config.yaml
result_companion/core/html/__init__.py
result_companion/core/html/html_creator.py
result_companion/core/html/llm_injector.py
result_companion/core/parsers/__init__.py
result_companion/core/parsers/config.py
result_companion/core/parsers/result_parser.py
result_companion/core/results/__init__.py
result_companion/core/results/visitors.py
result_companion/core/utils/__init__.py
result_companion/core/utils/log_levels.py
result_companion/core/utils/logging_config.py
result_companion/core/utils/progress.py
result_companion/entrypoints/__init__.py
result_companion/entrypoints/cli/__init__.py
result_companion/entrypoints/cli/cli_app.py
result_companion/entrypoints/run_rc.py
result_companion-0.0.2.dist-info/METADATA
result_companion-0.0.2.dist-info/WHEEL
result_companion-0.0.2.dist-info/entry_points.txt
result_companion-0.0.2.dist-info/licenses/LICENSE
result_companion-0.0.2.dist-info/RECORD
