Metadata-Version: 2.4
Name: result-companion
Version: 0.0.2
Summary: AI-powered analysis of Robot Framework test failures - instant insights from output.xml
License: Apache-2.0
License-File: LICENSE
Keywords: robotframework,testing,ai,llm,test-analysis,ollama,openai
Author: Milosz Trojanowski
Author-email: mil.troj@gmail.com
Requires-Python: >=3.10,<4.0
Classifier: Development Status :: 4 - Beta
Classifier: Environment :: Console
Classifier: Intended Audience :: Developers
Classifier: License :: OSI Approved :: Apache Software License
Classifier: Programming Language :: Python :: 3
Classifier: Programming Language :: Python :: 3.10
Classifier: Programming Language :: Python :: 3.11
Classifier: Programming Language :: Python :: 3.12
Classifier: Programming Language :: Python :: 3.13
Classifier: Programming Language :: Python :: 3.14
Classifier: Topic :: Software Development :: Testing
Requires-Dist: langchain-anthropic (>=0.3.7,<0.4.0)
Requires-Dist: langchain-aws (>=0.2.10,<0.3.0)
Requires-Dist: langchain-community (>=0.3.9,<0.4.0)
Requires-Dist: langchain-google-genai (>=2.1.6,<3.0.0)
Requires-Dist: langchain-ollama (>=0.2.1,<0.3.0)
Requires-Dist: langchain-openai (>=0.2.11,<0.3.0)
Requires-Dist: langchain-text-splitters (>=0.3.4,<0.4.0)
Requires-Dist: ollama (>=0.4.0,<0.5.0)
Requires-Dist: python-dotenv (>=1.0.1,<2.0.0)
Requires-Dist: pyyaml (>=6.0.2,<7.0.0)
Requires-Dist: robotframework (>=7.1.1,<8.0.0)
Requires-Dist: tiktoken (>=0.8.0,<0.9.0)
Requires-Dist: tqdm (>=4.67.1,<5.0.0)
Requires-Dist: typer (>=0.15.1,<0.16.0)
Project-URL: Homepage, https://github.com/miltroj/result-companion
Project-URL: Repository, https://github.com/miltroj/result-companion
